{
  "stats": {
    "suites": 1,
    "tests": 1,
    "passes": 1,
    "pending": 0,
    "failures": 0,
    "start": "2021-02-12T21:42:17.730Z",
    "end": "2021-02-12T21:42:18.294Z",
    "duration": 564
  },
  "suites": [
    {
      "title": "Ponyracer",
      "tests": [
        {
          "fullTitle": "Ponyracer should display title on home page",
          "title": "should display title on home page",
          "duration": 510,
          "result": "passed",
          "err": {}
        }
      ]
    }
  ],
  "pending": [],
  "failures": [],
  "passes": [
    {
      "fullTitle": "Ponyracer should display title on home page",
      "title": "should display title on home page",
      "duration": 510,
      "result": "passed",
      "err": {}
    }
  ]
}